Metadata-Version: 2.1
Name: pintrace
Version: 0.3.2
Summary: PinTrace is a useful tracing library. With easiest usage, just add decorators like Java annotation then able to log, trace and get latency in anywhere.
Home-page: https://github.com/superoutput/pintrace
Author: Savage Lasa
Author-email: superoutput@gmail.com
License: Savage
Keywords: pintrace python trace tracing library annotation add-on decorator wrapper
Platform: UNKNOWN
